vloglab/Lab3a/alu.v
module alu(alu_out, accum, data, opcode, zero, clk, reset);
input 		clk, reset;
input 	[7:0] 	accum, data;
input 	[2:0] 	opcode;
output 	[7:0] 	alu_out;
output 		zero;




endmodule

vloglab/Lab3a/alu_test.v
/*********************************************************************
 * Stimulus for the ALU design - Verilog Training Course
 *********************************************************************/
`timescale 1ns / 1ns
module alu_test;
  wire [7:0] alu_out;
  reg  [7:0] data, accum;
  reg  [2:0] opcode;
  integer    i, err_cnt, k;
  wire [7:0] twocomp_accum, cal_accum_data, cnd_accum;
  wire [7:0] abs_accum;
  reg clk, reset;
  
  parameter ranseed = 7;
  
// Instantiate the ALU.  Named mapping allows the designer to have freedom
//    with the order of port declarations

  alu   alu1 (.alu_out(alu_out), .zero(zero),               //outputs from ALU
	      .opcode(opcode), .data(data), .accum(accum), .clk(clk), .reset(reset)); //inputs to ALU

  //define mnemonics to represent opcodes
  `define PASSA 3'b000
  `define ADD   3'b001
  `define SUB   3'b010
  `define AND   3'b011
  `define XOR   3'b100
  `define ABS   3'b101
  `define CAL   3'b110
  `define CND 	3'b111

// Define a safe delay between each strobing of the ALU inputs/outputs
  `define strobe      20
  `define testnumber  10
assign cnd_accum = (accum>=32)? data : ~data ;
  
assign cal_accum_data = ((accum<<2)+accum) + (accum>>3);  
  
assign  twocomp_accum = ~accum + 8'b1;

assign  abs_accum = twocomp_accum;

// clock generate
initial   clk = 0;
always #(`strobe/2) clk = ~clk;

// pattern generate
  initial
    begin
    
       // SET UP THE GRAPHICAL WAVEFORM DISPLAY
      $shm_open("alu.shm");
      $shm_probe(alu_out,data,accum,opcode,zero);
      $fsdbDumpfile("alu.fsdb");
      $fsdbDumpvars();
      
      // SET UP THE OUTPUT FORMAT FOR THE TEXT DISPLAY
      $display("\t\t\t            INPUTS                   EXPECTD OUTPUTS       REAL    OUTPUT  \n");
      $display("\t\t\t  OPCODE   DATA IN    ACCUM IN  |  ALU OUT   ZERO BIT |  ALU OUT   ZERO BIT");
      $display("\t\t\t  ------   --------   --------  |  --------  -------- |  --------  --------");
      $timeformat(-9, 1, " ns", 9); //Display time in nanoseconds
      err_cnt = 0;   
      reset = 0;
      
      # `strobe;
      accum = 8'h37;
      data = 8'hD6;
      reset = 1;
      $display ("initial test, reset enable, alu_out = %b", alu_out);
      
      # `strobe;
        reset = 0;
	for (k = 0; k <= `testnumber; k = k+1)
	begin      
      		for (i = 0; i <= 7; i = i+1)  //VERIFY OPERATION FOR ALL 8 OPCODES
        		begin
			@(negedge clk)
			//change inputs at strobe point
          		#(`strobe/4) opcode = i;
			// APPLY STIMULUS TO THE INPUT PINS
			accum = $random % ranseed;                //Initialize inputs to the ALU
      			data = $random % ranseed;
          		//Wait for ALU to process inputs
          		#(`strobe/2)   check_outputs; //call a task to verify outputs
        		end
		
      		//VERIFY OPERATION WITH UNKNOWN OPCODE
      		@(negedge clk)  #(`strobe/4)  opcode = 3'b00x;
      		#(`strobe/2)   check_outputs;

      		//VERIFY OPERATION OF ZERO BIT
     		@(negedge clk) #(`strobe/4) accum = 8'h00; opcode = `ADD;
      		#(`strobe/2)   check_outputs;
		
	end
	
      //WAIT 1 MORE STROBE AND THEN FINISH
      #`strobe 
      if (err_cnt) $display("\nFAIL!! There were %d errors in all.\n", err_cnt);
      else $display("\nPASS!! No errors were found!\n");
      $finish;
    end

/**********************************************************************
 * SUBROUTINES TO COMPARE THE ALU OUTPUTS TO EXPECTED RESULTS
 *********************************************************************/
  task check_outputs;
    casez (opcode)
       `PASSA  : begin
                  $display("000 OPERATION	    :",
                           "      %b     %b   %b  |  %b      %b    |  %b      %b",
                           opcode, data, accum, accum, !accum, alu_out, zero);
                  if ((alu_out !== accum) || (zero !== !accum)) error;
                 end
       `ADD    : begin
                   $display("001 OPERATION       :",
                            "      %b     %b   %b  |  %b      %b    |  %b      %b",
                            opcode, data, accum, (accum+data), !accum, alu_out, zero);
                   if ((alu_out !== (accum + data)) || (zero !== !accum)) error;
                 end
       `SUB    : begin
                   $display("010 OPERATION       :",
                            "      %b     %b   %b  |  %b      %b    |  %b      %b",
                            opcode, data, accum, (accum-data), !accum, alu_out, zero);
                   if ((alu_out !== (accum - data)) || (zero !== !accum)) error;
                 end
       `AND    : begin
                   $display("011 OPERATION       :",
                            "      %b     %b   %b  |  %b      %b    |  %b      %b",
                            opcode, data, accum, (accum&data), !accum, alu_out, zero);
                   if ((alu_out !== (accum & data)) || (zero !== !accum)) error;
                 end
        `XOR   : begin
                   $display("100 OPERATION       :",
                           "      %b     %b   %b  |  %b      %b    |  %b      %b",
                           opcode, data, accum, (accum^data), !accum, alu_out, zero);
                   if ((alu_out !== (accum ^ data)) || (zero !== !accum)) error;
                 end
	`ABS    : begin
                   $display("101 OPERATION       :",
                            "      %b     %b   %b  |  %b      %b    |  %b      %b",
                            opcode, data, accum, abs_accum, !accum, alu_out, zero);
                   if ((alu_out !== abs_accum) || (zero !== !accum)) error;
                 end
	`CAL    : begin
                   $display("110 OPERATION       :",
                            "      %b     %b   %b  |  %b      %b    |  %b      %b",
                            opcode, data, accum, cal_accum_data, !accum, alu_out, zero);
                   if ((alu_out !== cal_accum_data) || (zero !== !accum)) error;
                 end
        `CND  : begin
                   $display("111 OPERATION       :",
                            "      %b     %b   %b  |  %b      %b    |  %b      %b",
                            opcode, data, accum, cnd_accum, !accum, alu_out, zero);
                   if ((alu_out !== cnd_accum) || (zero !== !accum)) error;
                 end
       default : begin
                   $display("UNKNOWN OPERATION   :",
                            "      %b     %b   %b  |  %b      %b    |  %b      %b",
                            opcode, data, accum, 8'b0, !accum,alu_out, zero);
                   if ((alu_out !== 8'b0) || (zero !== !accum)) error;
                 end
    endcase
  endtask

  task error;
    begin
      $display("\t\t\t ERROR AT %t,  ERROR OUTPUT : ALU_OUT = %b, ZERO_BIT = %b\n",
               $realtime, alu_out, zero);
      err_cnt = err_cnt + 1;
    end
  endtask

endmodule

vloglab/Lab3a/LBP.vcd
$date
	Thu Oct 13 19:54:15 2022
$end
$version
	Icarus Verilog
$end
$timescale
	1ns
$end
$scope module alu_test $end
$var wire 8 ! abs_accum [7:0] $end
$var wire 1 " zero $end
$var wire 8 # twocomp_accum [7:0] $end
$var wire 8 $ cnd_accum [7:0] $end
$var wire 8 % cal_accum_data [7:0] $end
$var wire 8 & alu_out [7:0] $end
$var parameter 32 ' ranseed $end
$var reg 8 ( accum [7:0] $end
$var reg 1 ) clk $end
$var reg 8 * data [7:0] $end
$var reg 3 + opcode [2:0] $end
$var reg 1 , reset $end
$var integer 32 - err_cnt [31:0] $end
$var integer 32 . i [31:0] $end
$var integer 32 / k [31:0] $end
$scope module alu1 $end
$var wire 8 0 accum [7:0] $end
$var wire 1 ) clk $end
$var wire 8 1 data [7:0] $end
$var wire 3 2 opcode [2:0] $end
$var wire 1 , reset $end
$var wire 1 " zero $end
$var reg 8 3 alu_out [7:0] $end
$upscope $end
$scope task check_outputs $end
$upscope $end
$scope task error $end
$upscope $end
$upscope $end
$enddefinitions $end
$comment Show the parameter values. $end
$dumpall
b111 '
$end
#0
$dumpvars
bx 3
bx 2
bx 1
bx 0
bx /
bx .
b0 -
0,
bx +
bx *
0)
bx (
bx &
bx %
bx $
bx #
x"
bx !
$end
#10
1)
#20
b0 &
b0 3
b11010110 $
b11001 %
0"
b11001001 !
b11001001 #
0)
1,
b11010110 *
b11010110 1
b110111 (
b110111 0
#30
1)
#40
0)
b0 .
b0 /
0,
#45
b101 $
1"
b0 !
b0 #
b11111010 *
b11111010 1
b0 %
b0 (
b0 0
b0 +
b0 2
#50
1)
#55
b1 .
#60
0)
#65
b11111101 $
0"
b11 !
b11 #
b11111101 *
b11111101 1
b10000 %
b11111101 (
b11111101 0
b1 +
b1 2
#70
b11111010 &
b11111010 3
1)
#75
b10 .
#80
0)
#85
b11111101 $
b11111010 !
b11111010 #
b10 *
b10 1
b11110 %
b110 (
b110 0
b10 +
b10 2
#90
b100 &
b100 3
1)
#95
b11 .
#100
0)
#105
b11111010 $
b110 !
b110 #
b11111010 *
b11111010 1
b1 %
b11111010 (
b11111010 0
b11 +
b11 2
#110
b11111010 &
b11111010 3
1)
#115
b100 .
#120
0)
#125
b11111101 $
b11111110 !
b11111110 #
b10 *
b10 1
b1010 %
b10 (
b10 0
b100 +
b100 2
#130
b0 &
b0 3
1)
#135
b101 .
#140
0)
#145
b11111100 $
1"
b0 !
b0 #
b11 *
b11 1
b0 %
b0 (
b0 0
b101 +
b101 2
#150
1)
#155
b110 .
#160
0)
#165
b11111111 $
b0 *
b0 1
b110 +
b110 2
#170
1)
#175
b111 .
#180
0)
#185
b11 $
0"
b11111011 !
b11111011 #
b11111100 *
b11111100 1
b11001 %
b101 (
b101 0
b111 +
b111 2
#190
b11111010 &
b11111010 3
1)
#195
b1000 .
b1 -
#200
0)
#205
b0x +
b0x 2
#210
1)
#215
b10 -
#220
0)
#225
1"
b0 !
b0 #
b1 +
b1 2
b0 %
b0 (
b0 0
#230
b11111100 &
b11111100 3
1)
#235
b0 .
b1 /
#240
0)
#245
b11111101 $
0"
b1 !
b1 #
b11111101 *
b11111101 1
b11010 %
b11111111 (
b11111111 0
b0 +
b0 2
#250
b11111111 &
b11111111 3
1)
#255
b1 .
#260
0)
#265
b100 $
b11111111 !
b11111111 #
b11111011 *
b11111011 1
b101 %
b1 (
b1 0
b1 +
b1 2
#270
b11111100 &
b11111100 3
1)
#275
b10 .
#280
0)
#285
b1 $
b110 !
b110 #
b1 *
b1 1
b1 %
b11111010 (
b11111010 0
b10 +
b10 2
#290
b11111001 &
b11111001 3
1)
#295
b11 .
#300
0)
#305
b100 $
b11111100 !
b11111100 #
b11111011 *
b11111011 1
b10100 %
b100 (
b100 0
b11 +
b11 2
#310
b0 &
b0 3
1)
#315
b100 .
#320
0)
#325
b11111010 $
b110 !
b110 #
b11111010 *
b11111010 1
b1 %
b11111010 (
b11111010 0
b100 +
b100 2
#330
1)
#335
b101 .
#340
0)
#345
b10 $
b11111100 !
b11111100 #
b11111101 *
b11111101 1
b10100 %
b100 (
b100 0
b101 +
b101 2
#350
b11111100 &
b11111100 3
1)
#355
b110 .
#360
0)
#365
b11111110 $
b100 !
b100 #
b11111110 *
b11111110 1
b1011 %
b11111100 (
b11111100 0
b110 +
b110 2
#370
b1011 &
b1011 3
1)
#375
b111 .
#380
0)
#385
b1 $
b110 !
b110 #
b1 *
b1 1
b1 %
b11111010 (
b11111010 0
b111 +
b111 2
#390
b1 &
b1 3
1)
#395
b1000 .
#400
0)
#405
b0x +
b0x 2
#410
1)
#415
b11 -
#420
0)
#425
b11111110 $
1"
b0 !
b0 #
b1 +
b1 2
b0 %
b0 (
b0 0
#430
1)
#435
b0 .
b10 /
#440
0)
#445
b10 $
0"
b100 !
b100 #
b10 *
b10 1
b1011 %
b11111100 (
b11111100 0
b0 +
b0 2
#450
b11111100 &
b11111100 3
1)
#455
b1 .
#460
0)
#465
b101 $
b11111111 !
b11111111 #
b11111010 *
b11111010 1
b101 %
b1 (
b1 0
b1 +
b1 2
#470
b11111011 &
b11111011 3
1)
#475
b10 .
#480
0)
#485
b11111011 $
b100 !
b100 #
b11111011 *
b11111011 1
b1011 %
b11111100 (
b11111100 0
b10 +
b10 2
#490
b1 &
b1 3
1)
#495
b11 .
#500
0)
#505
b11111100 $
b110 !
b110 #
b11111100 *
b11111100 1
b1 %
b11111010 (
b11111010 0
b11 +
b11 2
#510
b11111000 &
b11111000 3
1)
#515
b100 .
#520
0)
#525
b1 $
b11111100 !
b11111100 #
b11111110 *
b11111110 1
b10100 %
b100 (
b100 0
b100 +
b100 2
#530
b11111010 &
b11111010 3
1)
#535
b101 .
#540
0)
#545
b11111111 $
1"
b0 !
b0 #
b0 *
b0 1
b0 %
b0 (
b0 0
b101 +
b101 2
#550
b0 &
b0 3
1)
#555
b110 .
#560
0)
#565
b11 $
0"
b11111111 !
b11111111 #
b11111100 *
b11111100 1
b101 %
b1 (
b1 0
b110 +
b110 2
#570
b101 &
b101 3
1)
#575
b111 .
#580
0)
#585
b11111100 $
b11111010 !
b11111010 #
b11 *
b11 1
b11110 %
b110 (
b110 0
b111 +
b111 2
#590
b11111001 &
b11111001 3
1)
#595
b1000 .
b100 -
#600
0)
#605
b0x +
b0x 2
#610
1)
#615
b101 -
#620
0)
#625
1"
b0 !
b0 #
b1 +
b1 2
b0 %
b0 (
b0 0
#630
b11 &
b11 3
1)
#635
b0 .
b11 /
#640
0)
#645
b0 $
0"
b11 !
b11 #
b0 *
b0 1
b10000 %
b11111101 (
b11111101 0
b0 +
b0 2
#650
b11111101 &
b11111101 3
1)
#655
b1 .
#660
0)
#665
b11111110 $
b11111100 !
b11111100 #
b1 *
b1 1
b10100 %
b100 (
b100 0
b1 +
b1 2
#670
b101 &
b101 3
1)
#675
b10 .
#680
0)
#685
b101 $
b11111111 !
b11111111 #
b11111010 *
b11111010 1
b101 %
b1 (
b1 0
b10 +
b10 2
#690
b111 &
b111 3
1)
#695
b11 .
#700
0)
#705
b1 $
b11111011 !
b11111011 #
b11111110 *
b11111110 1
b11001 %
b101 (
b101 0
b11 +
b11 2
#710
b100 &
b100 3
1)
#715
b100 .
#720
0)
#725
b11111101 $
1"
b0 !
b0 #
b10 *
b10 1
b0 %
b0 (
b0 0
b100 +
b100 2
#730
b10 &
b10 3
1)
#735
b101 .
#740
0)
#745
b11111110 $
0"
b11111111 !
b11111111 #
b1 *
b1 1
b101 %
b1 (
b1 0
b101 +
b101 2
#750
b11111111 &
b11111111 3
1)
#755
b110 .
#760
0)
#765
b100 $
b11 !
b11 #
b100 *
b100 1
b10000 %
b11111101 (
b11111101 0
b110 +
b110 2
#770
b10000 &
b10000 3
1)
#775
b111 .
#780
0)
#785
b11111101 $
b100 !
b100 #
b11111101 *
b11111101 1
b1011 %
b11111100 (
b11111100 0
b111 +
b111 2
#790
b11111101 &
b11111101 3
1)
#795
b1000 .
#800
0)
#805
b0x +
b0x 2
#810
1)
#815
b110 -
#820
0)
#825
b10 $
1"
b0 !
b0 #
b1 +
b1 2
b0 %
b0 (
b0 0
#830
1)
#835
b0 .
b100 /
#840
0)
#845
b11111011 $
0"
b11111011 !
b11111011 #
b100 *
b100 1
b11001 %
b101 (
b101 0
b0 +
b0 2
#850
b101 &
b101 3
1)
#855
b1 .
#860
0)
#865
b10 $
b100 !
b100 #
b10 *
b10 1
b1011 %
b11111100 (
b11111100 0
b1 +
b1 2
#870
b11111110 &
b11111110 3
1)
#875
b10 .
#880
0)
#885
b110 $
b101 !
b101 #
b110 *
b110 1
b110 %
b11111011 (
b11111011 0
b10 +
b10 2
#890
b11110101 &
b11110101 3
1)
#895
b11 .
#900
0)
#905
b11111001 $
b11111111 !
b11111111 #
b101 %
b1 (
b1 0
b11 +
b11 2
#910
b0 &
b0 3
1)
#915
b100 .
#920
0)
#925
1"
b0 !
b0 #
b0 %
b0 (
b0 0
b100 +
b100 2
#930
b110 &
b110 3
1)
#935
b101 .
#940
0)
#945
b11111100 $
0"
b11111100 !
b11111100 #
b11 *
b11 1
b10100 %
b100 (
b100 0
b101 +
b101 2
#950
b11111100 &
b11111100 3
1)
#955
b110 .
#960
0)
#965
b100 $
b11111010 !
b11111010 #
b11111011 *
b11111011 1
b11110 %
b110 (
b110 0
b110 +
b110 2
#970
b11110 &
b11110 3
1)
#975
b111 .
#980
0)
#985
b11111110 $
b1 !
b1 #
b11111110 *
b11111110 1
b11010 %
b11111111 (
b11111111 0
b111 +
b111 2
#990
b11111110 &
b11111110 3
1)
#995
b1000 .
#1000
0)
#1005
b0x +
b0x 2
#1010
1)
#1015
b111 -
#1020
0)
#1025
b1 $
1"
b0 !
b0 #
b1 +
b1 2
b0 %
b0 (
b0 0
#1030
1)
#1035
b0 .
b101 /
#1040
0)
#1045
0"
b1 !
b1 #
b1 *
b1 1
b11010 %
b11111111 (
b11111111 0
b0 +
b0 2
#1050
b11111111 &
b11111111 3
1)
#1055
b1 .
#1060
0)
#1065
b11111110 $
b11 !
b11 #
b11111110 *
b11111110 1
b10000 %
b11111101 (
b11111101 0
b1 +
b1 2
#1070
b11111011 &
b11111011 3
1)
#1075
b10 .
#1080
0)
#1085
b0 $
1"
b0 !
b0 #
b11111111 *
b11111111 1
b0 %
b0 (
b0 0
b10 +
b10 2
#1090
b1 &
b1 3
1)
#1095
b11 .
#1100
0)
#1105
b11111100 $
0"
b11111101 !
b11111101 #
b11 *
b11 1
b1111 %
b11 (
b11 0
b11 +
b11 2
#1110
b11 &
b11 3
1)
#1115
b100 .
#1120
0)
#1125
b1 $
b11 !
b11 #
b1 *
b1 1
b10000 %
b11111101 (
b11111101 0
b100 +
b100 2
#1130
b11111100 &
b11111100 3
1)
#1135
b101 .
#1140
0)
#1145
b100 $
b10 !
b10 #
b100 *
b100 1
b10101 %
b11111110 (
b11111110 0
b101 +
b101 2
#1150
b10 &
b10 3
1)
#1155
b110 .
#1160
0)
#1165
b101 $
b11111101 !
b11111101 #
b11111010 *
b11111010 1
b1111 %
b11 (
b11 0
b110 +
b110 2
#1170
b1111 &
b1111 3
1)
#1175
b111 .
#1180
0)
#1185
b11111110 $
b1 *
b1 1
b111 +
b111 2
#1190
b11111100 &
b11111100 3
1)
#1195
b1000 .
b1000 -
#1200
0)
#1205
b0x +
b0x 2
#1210
1)
#1215
b1001 -
#1220
0)
#1225
1"
b0 !
b0 #
b1 +
b1 2
b0 %
b0 (
b0 0
#1230
b1 &
b1 3
1)
#1235
b0 .
b110 /
#1240
0)
#1245
b10 $
0"
b11111110 !
b11111110 #
b11111101 *
b11111101 1
b1010 %
b10 (
b10 0
b0 +
b0 2
#1250
b10 &
b10 3
1)
#1255
b1 .
#1260
0)
#1265
b0 $
b11111111 *
b11111111 1
b1 +
b1 2
#1270
b1 &
b1 3
1)
#1275
b10 .
#1280
0)
#1285
b11111110 $
b11111100 !
b11111100 #
b1 *
b1 1
b10100 %
b100 (
b100 0
b10 +
b10 2
#1290
b11 &
b11 3
1)
#1295
b11 .
#1300
0)
#1305
b11 $
b10 !
b10 #
b11 *
b11 1
b10101 %
b11111110 (
b11111110 0
b11 +
b11 2
#1310
b10 &
b10 3
1)
#1315
b100 .
#1320
0)
#1325
b11 $
b11111101 !
b11111101 #
b11111100 *
b11111100 1
b1111 %
b11 (
b11 0
b100 +
b100 2
#1330
b11111111 &
b11111111 3
1)
#1335
b101 .
#1340
0)
#1345
b11111111 $
b100 !
b100 #
b11111111 *
b11111111 1
b1011 %
b11111100 (
b11111100 0
b101 +
b101 2
#1350
b100 &
b100 3
1)
#1355
b110 .
#1360
0)
#1365
b11111111 $
b11111111 !
b11111111 #
b0 *
b0 1
b101 %
b1 (
b1 0
b110 +
b110 2
#1370
b101 &
b101 3
1)
#1375
b111 .
#1380
0)
#1385
b101 $
b11111100 !
b11111100 #
b11111010 *
b11111010 1
b10100 %
b100 (
b100 0
b111 +
b111 2
#1390
b11111011 &
b11111011 3
1)
#1395
b1000 .
b1010 -
#1400
0)
#1405
b0x +
b0x 2
#1410
1)
#1415
b1011 -
#1420
0)
#1425
1"
b0 !
b0 #
b1 +
b1 2
b0 %
b0 (
b0 0
#1430
b11111010 &
b11111010 3
1)
#1435
b0 .
b111 /
#1440
0)
#1445
b11111100 $
0"
b100 !
b100 #
b11111100 *
b11111100 1
b1011 %
b11111100 (
b11111100 0
b0 +
b0 2
#1450
b11111100 &
b11111100 3
1)
#1455
b1 .
#1460
0)
#1465
b101 $
b1 !
b1 #
b101 *
b101 1
b11010 %
b11111111 (
b11111111 0
b1 +
b1 2
#1470
b100 &
b100 3
1)
#1475
b10 .
#1480
0)
#1485
b100 $
b11111110 !
b11111110 #
b11111011 *
b11111011 1
b1010 %
b10 (
b10 0
b10 +
b10 2
#1490
b111 &
b111 3
1)
#1495
b11 .
#1500
0)
#1505
b110 $
b100 !
b100 #
b110 *
b110 1
b1011 %
b11111100 (
b11111100 0
b11 +
b11 2
#1510
b100 &
b100 3
1)
#1515
b100 .
#1520
0)
#1525
b1 $
b11111111 !
b11111111 #
b11111110 *
b11111110 1
b101 %
b1 (
b1 0
b100 +
b100 2
#1530
b11111111 &
b11111111 3
1)
#1535
b101 .
#1540
0)
#1545
b11111110 $
b1 !
b1 #
b11010 %
b11111111 (
b11111111 0
b101 +
b101 2
#1550
b1 &
b1 3
1)
#1555
b110 .
#1560
0)
#1565
b100 $
1"
b0 !
b0 #
b11111011 *
b11111011 1
b0 %
b0 (
b0 0
b110 +
b110 2
#1570
b0 &
b0 3
1)
#1575
b111 .
#1580
0)
#1585
b11111101 $
b10 *
b10 1
b111 +
b111 2
#1590
b11111111 &
b11111111 3
1)
#1595
b1000 .
b1100 -
#1600
0)
#1605
b0x +
b0x 2
#1610
1)
#1615
b1101 -
#1620
0)
#1625
b1 +
b1 2
#1630
b10 &
b10 3
1)
#1635
b0 .
b1000 /
#1640
0)
#1645
b110 $
0"
b101 !
b101 #
b110 *
b110 1
b110 %
b11111011 (
b11111011 0
b0 +
b0 2
#1650
b11111011 &
b11111011 3
1)
#1655
b1 .
#1660
0)
#1665
b11111111 $
b11111011 !
b11111011 #
b0 *
b0 1
b11001 %
b101 (
b101 0
b1 +
b1 2
#1670
b101 &
b101 3
1)
#1675
b10 .
#1680
0)
#1685
b11111100 !
b11111100 #
b10100 %
b100 (
b100 0
b10 +
b10 2
#1690
b100 &
b100 3
1)
#1695
b11 .
#1700
0)
#1705
b11111100 $
b10 !
b10 #
b11111100 *
b11111100 1
b10101 %
b11111110 (
b11111110 0
b11 +
b11 2
#1710
b11111100 &
b11111100 3
1)
#1715
b100 .
#1720
0)
#1725
b11111100 $
b11111010 !
b11111010 #
b11 *
b11 1
b11110 %
b110 (
b110 0
b100 +
b100 2
#1730
b101 &
b101 3
1)
#1735
b101 .
#1740
0)
#1745
b11111101 $
b110 !
b110 #
b11111101 *
b11111101 1
b1 %
b11111010 (
b11111010 0
b101 +
b101 2
#1750
b110 &
b110 3
1)
#1755
b110 .
#1760
0)
#1765
b10 $
b11111101 !
b11111101 #
b1111 %
b11 (
b11 0
b110 +
b110 2
#1770
b1111 &
b1111 3
1)
#1775
b111 .
#1780
0)
#1785
b11 $
b11111011 !
b11111011 #
b11111100 *
b11111100 1
b11001 %
b101 (
b101 0
b111 +
b111 2
#1790
b11111010 &
b11111010 3
1)
#1795
b1000 .
b1110 -
#1800
0)
#1805
b0x +
b0x 2
#1810
1)
#1815
b1111 -
#1820
0)
#1825
1"
b0 !
b0 #
b1 +
b1 2
b0 %
b0 (
b0 0
#1830
b11111100 &
b11111100 3
1)
#1835
b0 .
b1001 /
#1840
0)
#1845
b11111110 $
b1 *
b1 1
b0 +
b0 2
#1850
b0 &
b0 3
1)
#1855
b1 .
#1860
0)
#1865
b11111100 $
0"
b10 !
b10 #
b11111100 *
b11111100 1
b10101 %
b11111110 (
b11111110 0
b1 +
b1 2
#1870
b11111010 &
b11111010 3
1)
#1875
b10 .
#1880
0)
#1885
b11111111 $
b11111010 !
b11111010 #
b0 *
b0 1
b11110 %
b110 (
b110 0
b10 +
b10 2
#1890
b110 &
b110 3
1)
#1895
b11 .
#1900
0)
#1905
b10 $
b11111110 !
b11111110 #
b11111101 *
b11111101 1
b1010 %
b10 (
b10 0
b11 +
b11 2
#1910
b0 &
b0 3
1)
#1915
b100 .
#1920
0)
#1925
b110 $
b1 !
b1 #
b110 *
b110 1
b11010 %
b11111111 (
b11111111 0
b100 +
b100 2
#1930
b11111001 &
b11111001 3
1)
#1935
b101 .
#1940
0)
#1945
b11111100 $
b11111110 !
b11111110 #
b11 *
b11 1
b1010 %
b10 (
b10 0
b101 +
b101 2
#1950
b11111110 &
b11111110 3
1)
#1955
b110 .
#1960
0)
#1965
b100 $
b11 !
b11 #
b100 *
b100 1
b10000 %
b11111101 (
b11111101 0
b110 +
b110 2
#1970
b10000 &
b10000 3
1)
#1975
b111 .
#1980
0)
#1985
b11111001 $
b11111110 !
b11111110 #
b110 *
b110 1
b1010 %
b10 (
b10 0
b111 +
b111 2
#1990
b11111101 &
b11111101 3
1)
#1995
b1000 .
b10000 -
#2000
0)
#2005
b0x +
b0x 2
#2010
1)
#2015
b10001 -
#2020
0)
#2025
1"
b0 !
b0 #
b1 +
b1 2
b0 %
b0 (
b0 0
#2030
b110 &
b110 3
1)
#2035
b0 .
b1010 /
#2040
0)
#2045
b11111111 $
b0 *
b0 1
b0 +
b0 2
#2050
b0 &
b0 3
1)
#2055
b1 .
#2060
0)
#2065
b1 $
b11111110 *
b11111110 1
b1 +
b1 2
#2070
b11111110 &
b11111110 3
1)
#2075
b10 .
#2080
0)
#2085
b11111111 $
b0 *
b0 1
b10 +
b10 2
#2090
b0 &
b0 3
1)
#2095
b11 .
#2100
0)
#2105
b0 $
0"
b10 !
b10 #
b10101 %
b11111110 (
b11111110 0
b11 +
b11 2
#2110
1)
#2115
b100 .
#2120
0)
#2125
b110 $
b100 !
b100 #
b110 *
b110 1
b1011 %
b11111100 (
b11111100 0
b100 +
b100 2
#2130
b11111010 &
b11111010 3
1)
#2135
b101 .
#2140
0)
#2145
b101 $
b10 !
b10 #
b101 *
b101 1
b10101 %
b11111110 (
b11111110 0
b101 +
b101 2
#2150
b10 &
b10 3
1)
#2155
b110 .
#2160
0)
#2165
b11111010 $
b1 !
b1 #
b11111010 *
b11111010 1
b11010 %
b11111111 (
b11111111 0
b110 +
b110 2
#2170
b11010 &
b11010 3
1)
#2175
b111 .
#2180
0)
#2185
b11111111 $
b11111100 !
b11111100 #
b0 *
b0 1
b10100 %
b100 (
b100 0
b111 +
b111 2
#2190
b11111011 &
b11111011 3
1)
#2195
b1000 .
b10010 -
#2200
0)
#2205
b0x +
b0x 2
#2210
1)
#2215
b10011 -
#2220
0)
#2225
1"
b0 !
b0 #
b1 +
b1 2
b0 %
b0 (
b0 0
#2230
b0 &
b0 3
1)
#2235
b1011 /
